coomm/__init__.py
coomm/_rendering_tool.py
coomm/_rod_tool.py
coomm/actuations/__init__.py
coomm/actuations/actuation.py
coomm/actuations/muscles/__init__.py
coomm/actuations/muscles/longitudinal_muscle.py
coomm/actuations/muscles/muscle.py
coomm/actuations/muscles/oblique_muscle.py
coomm/actuations/muscles/transverse_muscle.py
coomm/algorithms/__init__.py
coomm/algorithms/algorithm.py
coomm/algorithms/forward_backward.py
coomm/algorithms/forward_backward_muscle.py
coomm/callback_func.py
coomm/forces/__init__.py
coomm/forces/drag_force.py
coomm/frames/__init__.py
coomm/frames/frame.py
coomm/frames/frame_tools.py
coomm/frames/muscle_frame.py
coomm/frames/rigidbody_frame.py
coomm/frames/rod_frame.py
coomm/objects/__init__.py
coomm/objects/cylinder.py
coomm/objects/director_constraint.py
coomm/objects/object.py
coomm/objects/point.py
coomm/objects/target.py
coomm/povray/__init__.py
coomm/povray/cylinder.py
coomm/povray/draw_sucker.py
coomm/povray/muscles/__init__.py
coomm/povray/muscles/muscle.py
coomm/povray/muscles/muscle_longitudinal.py
coomm/povray/muscles/muscle_oblique.py
coomm/povray/muscles/muscle_transverse.py
coomm/povray/povray_base.py
coomm/povray/povray_camera.py
coomm/povray/povray_frame.py
coomm/povray/rod.py
coomm/povray/sphere.py
coomm/version.py
coomm-0.1.1.dist-info/LICENSE
coomm-0.1.1.dist-info/METADATA
coomm-0.1.1.dist-info/WHEEL
coomm-0.1.1.dist-info/RECORD
