Metadata-Version: 2.1
Name: coomm
Version: 0.1.1
Summary: Control Oriented Muscle Model for an octopus arm.
License: MIT
Author: hanson-hschang
Author-email: hschang2@illinois.edu
Requires-Python: >=3.10,<3.11
Classifier: Development Status :: 4 - Beta
Classifier: Intended Audience :: Education
Classifier: Intended Audience :: Science/Research
Classifier: License :: OSI Approved :: MIT License
Classifier: Programming Language :: Python
Classifier: Programming Language :: Python :: 3
Classifier: Programming Language :: Python :: 3.10
Classifier: Programming Language :: Python :: 3.10
Classifier: Programming Language :: Python :: 3.8
Classifier: Programming Language :: Python :: 3.9
Requires-Dist: matplotlib (>=3.7.1,<4.0.0)
Requires-Dist: numba (>=0.55.0,<0.56.0)
Requires-Dist: numpy (>=1.19.2,<2.0.0)
Requires-Dist: pyelastica (>=0.3.1.post1,<0.4.0)
